{
  "name": "x-imartinstudio-appeal",
  "displayName": "X @iMartinstudio Appeal",
  "description": "Analyze X account @iMartinstudio suspension evidence and draft fact-grounded appeals without submitting them.",
  "version": "1.0.1",
  "author": "Martin",
  "type": "skill",
  "category": "social",
  "tags": ["x", "appeal", "suspension", "gmail", "account-security"],
  "scenarios": [
    "analyze-imartinstudio-suspension",
    "draft-imartinstudio-appeal",
    "update-imartinstudio-evidence"
  ],
  "path": "skills/x-imartinstudio-appeal",
  "entry": "SKILL.md",
  "license": "MIT",
  "compatibility": {
    "codexSkill": true,
    "mcp": false,
    "plugin": false
  }
}
